detectree2/__init__.py
detectree2/constants.py
detectree2/data_loading/__init__.py
detectree2/data_loading/gdrive.py
detectree2/data_loading/gdrive_load.py
detectree2/data_loading/gee_download.py
detectree2/data_loading/quickstart.py
detectree2/models/__init__.py
detectree2/models/evaluation.py
detectree2/models/models.py
detectree2/models/outputs.py
detectree2/models/predict.py
detectree2/models/test.py
detectree2/models/train.py
detectree2/models/train_tune.py
detectree2/preprocessing/__init__.py
detectree2/preprocessing/crowns.py
detectree2/preprocessing/tiling.py
detectree2/tests/__init__.py
detectree2/tests/test_all.py
detectree2/tests/test_data.py
detectree2/tests/test_evaluation.py
detectree2/tests/test_models.py
detectree2/tests/test_predict.py
detectree2/tests/test_preprocessing.py
detectree2-0.0.1.dist-info/LICENSE
detectree2-0.0.1.dist-info/METADATA
detectree2-0.0.1.dist-info/WHEEL
detectree2-0.0.1.dist-info/top_level.txt
detectree2-0.0.1.dist-info/RECORD
