Metadata-Version: 2.1
Name: detectree2
Version: 0.0.1
Summary: Detectree packaging
Home-page: https://github.com/PatBall1/detectree2
Author: James G. C. Ball
Author-email: ball.jgc@gmail.com.com
License: UNKNOWN
Platform: UNKNOWN
License-File: LICENSE
Requires-Dist: pyyaml (==5.1)
Requires-Dist: GDAL (>=1.11)
Requires-Dist: proj
Requires-Dist: geos
Requires-Dist: pypng
Requires-Dist: pygeos
Requires-Dist: geopandas
Requires-Dist: rasterio (==1.3.2)
Requires-Dist: fiona
Requires-Dist: pycrs
Requires-Dist: descartes
Requires-Dist: detectron2
